slurm2sql.py
slurm2sql-0.9.8.dist-info/entry_points.txt
slurm2sql-0.9.8.dist-info/licenses/LICENSE
slurm2sql-0.9.8.dist-info/WHEEL
slurm2sql-0.9.8.dist-info/METADATA
slurm2sql-0.9.8.dist-info/RECORD
