Metadata-Version: 2.4
Name: slurm2sql
Version: 0.9.8
Summary: Import Slurm accounting database from sacct to sqlite3 database
Keywords: slurm,sqlite3
Author: Richard Darst
Requires-Python: >=3.6
Classifier: Programming Language :: Python :: 2.7
Classifier: Programming Language :: Python :: 3
Classifier: License :: OSI Approved :: MIT License
Classifier: Operating System :: OS Independent
Classifier: Development Status :: 4 - Beta
Classifier: Environment :: Console
Classifier: Intended Audience :: System Administrators
Classifier: Topic :: Database
Classifier: Topic :: System :: Clustering
Classifier: Topic :: System :: Distributed Computing
License-File: LICENSE
Requires-Dist: tabulate
Requires-Dist: pytest ; extra == "test"
Project-URL: Repository, https://github.com/NordicHPC/slurm2sql
Provides-Extra: test
